dpt_xml/__init__.py
dpt_xml/abstract_xml_parser.py
dpt_xml/xml_parser.py
dpt_xml/xml_parser_MonoXML.py
dpt_xml/xml_parser_expat.py
dpt_xml/xml_resource.py
dpt_xml-1.0.3.data/data/docs/LICENSE
dpt_xml-1.0.3.data/data/docs/README
dpt_xml-1.0.3.dist-info/LICENSE
dpt_xml-1.0.3.dist-info/METADATA
dpt_xml-1.0.3.dist-info/WHEEL
dpt_xml-1.0.3.dist-info/top_level.txt
dpt_xml-1.0.3.dist-info/RECORD
