Metadata-Version: 2.1
Name: dpt-xml
Version: 1.0.3
Summary: Multiple XML parsers with a common abstraction layer
Home-page: https://www.direct-netware.de/redirect?dpt;xml
Author: direct Netware Group et al.
Author-email: web@direct-netware.de
License: MPL2
Platform: any
Classifier: Intended Audience :: Developers
Classifier: License :: OSI Approved :: Mozilla Public License 2.0 (MPL 2.0)
Classifier: Operating System :: OS Independent
Classifier: Programming Language :: Python
Classifier: Topic :: Software Development :: Libraries :: Python Modules
